bravado_core/__init__.py
bravado_core/_compat.py
bravado_core/_compat_typing.py
bravado_core/_decorators.py
bravado_core/content_type.py
bravado_core/docstring.py
bravado_core/exception.py
bravado_core/formatter.py
bravado_core/marshal.py
bravado_core/model.py
bravado_core/operation.py
bravado_core/param.py
bravado_core/py.typed
bravado_core/request.py
bravado_core/resource.py
bravado_core/response.py
bravado_core/schema.py
bravado_core/security_definition.py
bravado_core/security_requirement.py
bravado_core/spec.py
bravado_core/spec_flattening.py
bravado_core/swagger20_validator.py
bravado_core/unmarshal.py
bravado_core/util.py
bravado_core/validate.py
bravado_core-6.1.0.dist-info/LICENSE.txt
bravado_core-6.1.0.dist-info/METADATA
bravado_core-6.1.0.dist-info/WHEEL
bravado_core-6.1.0.dist-info/top_level.txt
bravado_core-6.1.0.dist-info/RECORD
