Metadata-Version: 2.1
Name: bravado-core
Version: 6.1.0
Summary: Library for adding Swagger support to clients and servers
Home-page: https://github.com/Yelp/bravado-core
Author: Digium, Inc. and Yelp, Inc.
Author-email: opensource+bravado-core@yelp.com
License: BSD 3-Clause License
Platform: UNKNOWN
Classifier: Development Status :: 5 - Production/Stable
Classifier: Intended Audience :: Developers
Classifier: Topic :: Software Development :: Libraries :: Python Modules
Classifier: License :: OSI Approved :: BSD License
Classifier: Operating System :: OS Independent
Classifier: Programming Language :: Python :: 3
Classifier: Programming Language :: Python :: 3.7
Classifier: Programming Language :: Python :: 3.8
Classifier: Programming Language :: Python :: 3.9
Classifier: Programming Language :: Python :: 3.10
Classifier: Programming Language :: Python :: 3.11
Requires-Python: >=3.7
License-File: LICENSE.txt
Requires-Dist: jsonref
Requires-Dist: jsonschema[format] (>=2.5.1)
Requires-Dist: msgpack (>=0.5.2)
Requires-Dist: python-dateutil
Requires-Dist: pytz
Requires-Dist: pyyaml
Requires-Dist: requests
Requires-Dist: simplejson
Requires-Dist: six
Requires-Dist: swagger-spec-validator (>=2.0.1)
